CMCLogger-0.0.1.data/scripts/CMCLogger
cmclogger/__init__.py
cmclogger/cmclogger.py
cmclogger/settings.py
cmclogger/api/__init__.py
cmclogger/api/getlatest.py
cmclogger/dataparser/__init__.py
cmclogger/dataparser/publisher.py
cmclogger/dataparser/reader.py
tests/__init__.py
tests/test_api_getlatest.py
tests/test_dataparser_publisher.py
tests/test_dataparser_reader.py
CMCLogger-0.0.1.dist-info/LICENSE
CMCLogger-0.0.1.dist-info/METADATA
CMCLogger-0.0.1.dist-info/WHEEL
CMCLogger-0.0.1.dist-info/top_level.txt
CMCLogger-0.0.1.dist-info/RECORD
