Metadata-Version: 2.1
Name: CMCLogger
Version: 0.0.1
Summary: Coin Market Cap Public API Cryptocurrency data logger
Home-page: https://github.com/stuianna/CMCLogger
Author: stuianna
Author-email: stuiaa@protonmail.com
License: UNKNOWN
Platform: UNKNOWN
Classifier: Programming Language :: Python :: 3
Classifier: License :: OSI Approved :: MIT License
Classifier: Operating System :: OS Independent
Requires-Python: >=3.6
Requires-Dist: pandas
Requires-Dist: numpy
Requires-Dist: db-ops
Requires-Dist: config-checker
Requires-Dist: python-dateutil
Requires-Dist: pytz
Requires-Dist: requests
Requires-Dist: urllib3
Requires-Dist: idna
Requires-Dist: certifi
Requires-Dist: appdirs
Requires-Dist: chardet
Requires-Dist: et-xmlfile
Requires-Dist: jdcal
Requires-Dist: openpyxl
